index.py
dell_recovery-99.99.99.dist-info/METADATA
dell_recovery-99.99.99.dist-info/WHEEL
dell_recovery-99.99.99.dist-info/top_level.txt
dell_recovery-99.99.99.dist-info/RECORD
