Metadata-Version: 2.1
Name: dell-recovery
Version: 99.99.99
Summary: Ethically claimed for security testing
